gramps_web_desktop/__init__.py
gramps_web_desktop/_version.py
gramps_web_desktop/main.py
gramps_web_desktop/frontend/0376c6a2.js
gramps_web_desktop/frontend/0a8de34b.css
gramps_web_desktop/frontend/1f56c99e.css
gramps_web_desktop/frontend/7da94e03.css
gramps_web_desktop/frontend/beda634a.js
gramps_web_desktop/frontend/config.js
gramps_web_desktop/frontend/global.css
gramps_web_desktop/frontend/index.html
gramps_web_desktop/frontend/manifest.json
gramps_web_desktop/frontend/maplibre-gl.css
gramps_web_desktop/frontend/sw.js
gramps_web_desktop/frontend/sw.js.map
gramps_web_desktop/frontend/tippy.css
gramps_web_desktop/frontend/workbox-cdc7dff5.js
gramps_web_desktop/frontend/workbox-cdc7dff5.js.map
gramps_web_desktop/frontend/assets/favicon.ico
gramps_web_desktop/frontend/assets/icon192.png
gramps_web_desktop/frontend/assets/manifest.json
gramps_web_desktop/frontend/fonts/CommitMono VariableFont.woff2
gramps_web_desktop/frontend/fonts/EBGaramond12-Italic.woff
gramps_web_desktop/frontend/fonts/EBGaramond12-Regular.woff
gramps_web_desktop/frontend/fonts/Inter-italic.var.woff2
gramps_web_desktop/frontend/fonts/Inter-roman.var.woff2
gramps_web_desktop/frontend/fonts/MaterialIcons.woff2
gramps_web_desktop/frontend/fonts/fonts.css
gramps_web_desktop/frontend/images/favicon.ico
gramps_web_desktop/frontend/images/icon192.png
gramps_web_desktop/frontend/images/icon512.png
gramps_web_desktop/frontend/images/layers-2x.png
gramps_web_desktop/frontend/images/layers.png
gramps_web_desktop/frontend/images/marker-icon-2x.png
gramps_web_desktop/frontend/images/marker-icon.png
gramps_web_desktop/frontend/images/marker-shadow.png
gramps_web_desktop/frontend/lang/ar.json
gramps_web_desktop/frontend/lang/ba.json
gramps_web_desktop/frontend/lang/bg.json
gramps_web_desktop/frontend/lang/br.json
gramps_web_desktop/frontend/lang/ca.json
gramps_web_desktop/frontend/lang/cs.json
gramps_web_desktop/frontend/lang/da.json
gramps_web_desktop/frontend/lang/de.json
gramps_web_desktop-0.0.4.dist-info/licenses/LICENSE
gramps_web_desktop-0.0.4.dist-info/METADATA
gramps_web_desktop-0.0.4.dist-info/WHEEL
gramps_web_desktop-0.0.4.dist-info/entry_points.txt
gramps_web_desktop-0.0.4.dist-info/top_level.txt
gramps_web_desktop-0.0.4.dist-info/RECORD
