Metadata-Version: 2.4
Name: gramps-web-desktop
Version: 0.0.4
Home-page: https://github.com/dsblank/gramps-web-desktop
Author: 
License: AGPL-3.0 license
Platform: Linux
Platform: Mac OS X
Platform: Windows
Requires-Python: >=3.7
License-File: LICENSE
Requires-Dist: setuptools
Requires-Dist: gramps>=5.2.0
Requires-Dist: gramps-webapi>=2.7.0
Dynamic: description
Dynamic: description-content-type
Dynamic: home-page
Dynamic: license
Dynamic: license-file
Dynamic: platform
Dynamic: requires-dist
Dynamic: requires-python
